playingcards.py
SimplePlayingCards-1.1.0.dist-info/DESCRIPTION.rst
SimplePlayingCards-1.1.0.dist-info/LICENSE.txt
SimplePlayingCards-1.1.0.dist-info/METADATA
SimplePlayingCards-1.1.0.dist-info/RECORD
SimplePlayingCards-1.1.0.dist-info/WHEEL
SimplePlayingCards-1.1.0.dist-info/metadata.json
SimplePlayingCards-1.1.0.dist-info/top_level.txt
