Metadata-Version: 2.0
Name: SimplePlayingCards
Version: 1.1.0
Summary: Simple pair of classes to represent playing cards in python games
Home-page: https://github.com/ccdale/playingcards
Author: Chris Allison
Author-email: chris.charles.allison+playingcards@gmail.com
License: MIT
Download-URL: https://github.com/ccdale/playingcards
Platform: UNKNOWN
Classifier: Development Status :: 4 - Beta
Classifier: Intended Audience :: Developers
Classifier: Topic :: Games/Entertainment
Classifier: Programming Language :: Python :: 2
Classifier: Programming Language :: Python :: 2.7
Classifier: Programming Language :: Python :: 3
Classifier: Programming Language :: Python :: 3.5
